zipatopy/__init__.py
zipatopy-0.4.dist-info/LICENSE
zipatopy-0.4.dist-info/METADATA
zipatopy-0.4.dist-info/WHEEL
zipatopy-0.4.dist-info/top_level.txt
zipatopy-0.4.dist-info/RECORD
