Metadata-Version: 2.1
Name: zipatopy
Version: 0.4
Summary: The Python library to interact with Zipato smarthome controllers
Home-page: https://github.com/goooroooX/ZipatoPy
Author: Dmitry Nikolaenya
License: Apache 2.0
Keywords: zipato api client
Platform: UNKNOWN
Classifier: Programming Language :: Python :: 2
Classifier: Programming Language :: Python :: 2.7
Classifier: Programming Language :: Python :: 3
Classifier: Programming Language :: Python :: 3.6
Classifier: Development Status :: 5 - Production/Stable
Classifier: Intended Audience :: Developers
Classifier: License :: OSI Approved :: Apache Software License
Classifier: Operating System :: OS Independent
Classifier: Topic :: Internet :: WWW/HTTP
